lu_dj_utils/__init__.py
lu_dj_utils/context_processors.py
lu_dj_utils/email.py
lu_dj_utils/form_fields.py
lu_dj_utils/hex.py
lu_dj_utils/log.py
lu_dj_utils/model_fields.py
lu_dj_utils/models.py
lu_dj_utils/normalization.py
lu_dj_utils/test.py
lu_dj_utils/urls.py
lu_dj_utils/views.py
lu_dj_utils-0.1.4.dist-info/DESCRIPTION.rst
lu_dj_utils-0.1.4.dist-info/METADATA
lu_dj_utils-0.1.4.dist-info/RECORD
lu_dj_utils-0.1.4.dist-info/WHEEL
lu_dj_utils-0.1.4.dist-info/metadata.json
lu_dj_utils-0.1.4.dist-info/top_level.txt
tests/__init__.py
tests/test_email.py
tests/test_hex.py
tests/test_normalization.py
tests/test_test.py
tests/test_urls.py
